{
    "uid": "28806724-d287-4156-99a5-d5e352015d19",
    "name": "102_DecisionTree",
    "preprocessing": [
        {
            "categorical_y": {
                "0": 0,
                "1": 1,
                "2": 2
            },
            "ml_task": "multiclass_classification",
            "params": {
                "columns_preprocessing": {},
                "target_preprocessing": [
                    "na_exclude",
                    "categorical_to_int"
                ],
                "ml_task": "multiclass_classification"
            }
        },
        {
            "categorical_y": {
                "0": 0,
                "1": 1,
                "2": 2
            },
            "ml_task": "multiclass_classification",
            "params": {
                "columns_preprocessing": {},
                "target_preprocessing": [
                    "na_exclude",
                    "categorical_to_int"
                ],
                "ml_task": "multiclass_classification"
            }
        },
        {
            "categorical_y": {
                "0": 0,
                "1": 1,
                "2": 2
            },
            "ml_task": "multiclass_classification",
            "params": {
                "columns_preprocessing": {},
                "target_preprocessing": [
                    "na_exclude",
                    "categorical_to_int"
                ],
                "ml_task": "multiclass_classification"
            }
        },
        {
            "categorical_y": {
                "0": 0,
                "1": 1,
                "2": 2
            },
            "ml_task": "multiclass_classification",
            "params": {
                "columns_preprocessing": {},
                "target_preprocessing": [
                    "na_exclude",
                    "categorical_to_int"
                ],
                "ml_task": "multiclass_classification"
            }
        },
        {
            "categorical_y": {
                "0": 0,
                "1": 1,
                "2": 2
            },
            "ml_task": "multiclass_classification",
            "params": {
                "columns_preprocessing": {},
                "target_preprocessing": [
                    "na_exclude",
                    "categorical_to_int"
                ],
                "ml_task": "multiclass_classification"
            }
        },
        {
            "categorical_y": {
                "0": 0,
                "1": 1,
                "2": 2
            },
            "ml_task": "multiclass_classification",
            "params": {
                "columns_preprocessing": {},
                "target_preprocessing": [
                    "na_exclude",
                    "categorical_to_int"
                ],
                "ml_task": "multiclass_classification"
            }
        },
        {
            "categorical_y": {
                "0": 0,
                "1": 1,
                "2": 2
            },
            "ml_task": "multiclass_classification",
            "params": {
                "columns_preprocessing": {},
                "target_preprocessing": [
                    "na_exclude",
                    "categorical_to_int"
                ],
                "ml_task": "multiclass_classification"
            }
        },
        {
            "categorical_y": {
                "0": 0,
                "1": 1,
                "2": 2
            },
            "ml_task": "multiclass_classification",
            "params": {
                "columns_preprocessing": {},
                "target_preprocessing": [
                    "na_exclude",
                    "categorical_to_int"
                ],
                "ml_task": "multiclass_classification"
            }
        },
        {
            "categorical_y": {
                "0": 0,
                "1": 1,
                "2": 2
            },
            "ml_task": "multiclass_classification",
            "params": {
                "columns_preprocessing": {},
                "target_preprocessing": [
                    "na_exclude",
                    "categorical_to_int"
                ],
                "ml_task": "multiclass_classification"
            }
        },
        {
            "categorical_y": {
                "0": 0,
                "1": 1,
                "2": 2
            },
            "ml_task": "multiclass_classification",
            "params": {
                "columns_preprocessing": {},
                "target_preprocessing": [
                    "na_exclude",
                    "categorical_to_int"
                ],
                "ml_task": "multiclass_classification"
            }
        }
    ],
    "learners": [
        {
            "library_version": "1.2.2",
            "algorithm_name": "Decision Tree",
            "algorithm_short_name": "Decision Tree",
            "uid": "977ebd55-a4ad-421f-b5b1-42d26b21cc26",
            "params": {
                "model_type": "Decision Tree",
                "ml_task": "multiclass_classification",
                "n_jobs": -1,
                "seed": 1235,
                "criterion": "entropy",
                "max_depth": 3,
                "num_class": 3,
                "explain_level": 0
            },
            "name": "learner_fold_0"
        },
        {
            "library_version": "1.2.2",
            "algorithm_name": "Decision Tree",
            "algorithm_short_name": "Decision Tree",
            "uid": "4f20449e-90ef-440b-ab04-28fa0afaaaaf",
            "params": {
                "model_type": "Decision Tree",
                "ml_task": "multiclass_classification",
                "n_jobs": -1,
                "seed": 1235,
                "criterion": "entropy",
                "max_depth": 3,
                "num_class": 3,
                "explain_level": 0
            },
            "name": "learner_fold_1"
        },
        {
            "library_version": "1.2.2",
            "algorithm_name": "Decision Tree",
            "algorithm_short_name": "Decision Tree",
            "uid": "bf27614c-c394-499b-ad17-2ec5c030fd25",
            "params": {
                "model_type": "Decision Tree",
                "ml_task": "multiclass_classification",
                "n_jobs": -1,
                "seed": 1235,
                "criterion": "entropy",
                "max_depth": 3,
                "num_class": 3,
                "explain_level": 0
            },
            "name": "learner_fold_2"
        },
        {
            "library_version": "1.2.2",
            "algorithm_name": "Decision Tree",
            "algorithm_short_name": "Decision Tree",
            "uid": "be5ef3ad-324c-4471-a6dd-8e54c4c1177c",
            "params": {
                "model_type": "Decision Tree",
                "ml_task": "multiclass_classification",
                "n_jobs": -1,
                "seed": 1235,
                "criterion": "entropy",
                "max_depth": 3,
                "num_class": 3,
                "explain_level": 0
            },
            "name": "learner_fold_3"
        },
        {
            "library_version": "1.2.2",
            "algorithm_name": "Decision Tree",
            "algorithm_short_name": "Decision Tree",
            "uid": "ac8232ad-654c-4382-aafc-790ed15349a3",
            "params": {
                "model_type": "Decision Tree",
                "ml_task": "multiclass_classification",
                "n_jobs": -1,
                "seed": 1235,
                "criterion": "entropy",
                "max_depth": 3,
                "num_class": 3,
                "explain_level": 0
            },
            "name": "learner_fold_4"
        },
        {
            "library_version": "1.2.2",
            "algorithm_name": "Decision Tree",
            "algorithm_short_name": "Decision Tree",
            "uid": "1ed9e550-a338-4bbd-8c68-16aa37e9ff51",
            "params": {
                "model_type": "Decision Tree",
                "ml_task": "multiclass_classification",
                "n_jobs": -1,
                "seed": 1235,
                "criterion": "entropy",
                "max_depth": 3,
                "num_class": 3,
                "explain_level": 0
            },
            "name": "learner_fold_5"
        },
        {
            "library_version": "1.2.2",
            "algorithm_name": "Decision Tree",
            "algorithm_short_name": "Decision Tree",
            "uid": "e5509b69-24b8-49ee-a1c4-19d80203df40",
            "params": {
                "model_type": "Decision Tree",
                "ml_task": "multiclass_classification",
                "n_jobs": -1,
                "seed": 1235,
                "criterion": "entropy",
                "max_depth": 3,
                "num_class": 3,
                "explain_level": 0
            },
            "name": "learner_fold_6"
        },
        {
            "library_version": "1.2.2",
            "algorithm_name": "Decision Tree",
            "algorithm_short_name": "Decision Tree",
            "uid": "d7635a5c-5679-4daf-8f1a-299c20db7bf5",
            "params": {
                "model_type": "Decision Tree",
                "ml_task": "multiclass_classification",
                "n_jobs": -1,
                "seed": 1235,
                "criterion": "entropy",
                "max_depth": 3,
                "num_class": 3,
                "explain_level": 0
            },
            "name": "learner_fold_7"
        },
        {
            "library_version": "1.2.2",
            "algorithm_name": "Decision Tree",
            "algorithm_short_name": "Decision Tree",
            "uid": "10fd286d-23f4-4400-8185-471cde1c4458",
            "params": {
                "model_type": "Decision Tree",
                "ml_task": "multiclass_classification",
                "n_jobs": -1,
                "seed": 1235,
                "criterion": "entropy",
                "max_depth": 3,
                "num_class": 3,
                "explain_level": 0
            },
            "name": "learner_fold_8"
        },
        {
            "library_version": "1.2.2",
            "algorithm_name": "Decision Tree",
            "algorithm_short_name": "Decision Tree",
            "uid": "c9f6ba07-86fa-4f09-b981-a33e7344146d",
            "params": {
                "model_type": "Decision Tree",
                "ml_task": "multiclass_classification",
                "n_jobs": -1,
                "seed": 1235,
                "criterion": "entropy",
                "max_depth": 3,
                "num_class": 3,
                "explain_level": 0
            },
            "name": "learner_fold_9"
        }
    ],
    "params": {
        "additional": {
            "trees_in_step": 1,
            "train_cant_improve_limit": 0,
            "max_steps": 1,
            "max_rows_limit": null,
            "max_cols_limit": null
        },
        "preprocessing": {
            "columns_preprocessing": {},
            "target_preprocessing": [
                "na_exclude",
                "categorical_to_int"
            ],
            "ml_task": "multiclass_classification"
        },
        "validation_strategy": {
            "validation_type": "kfold",
            "shuffle": true,
            "stratify": true,
            "X_path": "AutoML_1\\X.data",
            "y_path": "AutoML_1\\y.data",
            "results_path": "AutoML_1",
            "k_folds": 10
        },
        "learner": {
            "model_type": "Decision Tree",
            "ml_task": "multiclass_classification",
            "n_jobs": -1,
            "seed": 1235,
            "criterion": "entropy",
            "max_depth": 3,
            "num_class": 3,
            "explain_level": 0
        },
        "automl_random_state": 1234,
        "ml_task": "multiclass_classification",
        "explain_level": 0,
        "name": "102_DecisionTree",
        "status": "initialized",
        "final_loss": null,
        "train_time": null,
        "data_type": "original",
        "max_time_for_learner": 60
    },
    "saved": [
        "102_DecisionTree\\learner_fold_0.decision_tree",
        "102_DecisionTree\\learner_fold_1.decision_tree",
        "102_DecisionTree\\learner_fold_2.decision_tree",
        "102_DecisionTree\\learner_fold_3.decision_tree",
        "102_DecisionTree\\learner_fold_4.decision_tree",
        "102_DecisionTree\\learner_fold_5.decision_tree",
        "102_DecisionTree\\learner_fold_6.decision_tree",
        "102_DecisionTree\\learner_fold_7.decision_tree",
        "102_DecisionTree\\learner_fold_8.decision_tree",
        "102_DecisionTree\\learner_fold_9.decision_tree"
    ],
    "predictions_fname": "102_DecisionTree\\predictions_out_of_folds.csv",
    "metric_name": "logloss",
    "final_loss": "0.540788415396867",
    "train_time": 6.923081159591675,
    "is_stacked": false,
    "joblib_version": "1.3.2"
}